cadcad_machine_search/__init__.py
cadcad_machine_search/tools/__init__.py
cadcad_machine_search/tools/param_sweep.py
cadcad_machine_search/visualizations/__init__.py
cadcad_machine_search/visualizations/goal_impact.py
cadcad_machine_search/visualizations/sensitivity.py
cadCAD_machine_search-0.0.1.4.dist-info/LICENSE
cadCAD_machine_search-0.0.1.4.dist-info/METADATA
cadCAD_machine_search-0.0.1.4.dist-info/WHEEL
cadCAD_machine_search-0.0.1.4.dist-info/top_level.txt
cadCAD_machine_search-0.0.1.4.dist-info/RECORD
