Metadata-Version: 2.1
Name: cadCAD-machine-search
Version: 0.0.1.4
Summary: Tools for Large-Scale Machine Search for Parameter Optimization on cadCAD
Home-page: https://github.com/cadCAD-org/cadCAD_machine_search
Author: Danilo Lessa Bernardineli
Author-email: danilo@block.science, danilo.lessa@gmail.com
License: UNKNOWN
Platform: UNKNOWN
Requires-Dist: cadCAD
